counterpy/__init__.py
counterpy/counterpy.py
counterpy-1.0.0.dist-info/WHEEL
counterpy-1.0.0.dist-info/entry_points.txt
counterpy-1.0.0.dist-info/METADATA
counterpy-1.0.0.dist-info/RECORD
